corpus_patterns/__init__.py
corpus_patterns/asset_axioms.py
corpus_patterns/asset_builders.py
corpus_patterns/asset_extractors.py
corpus_patterns/build_abbreviations.py
corpus_patterns/build_digits.py
corpus_patterns/build_serials.py
corpus_patterns/ent_patterns_case.py
corpus_patterns/ent_patterns_item.py
corpus_patterns/patterns_date.py
corpus_patterns/patterns_docket.py
corpus_patterns/patterns_generic.py
corpus_patterns/patterns_juridical.py
corpus_patterns/patterns_report.py
corpus_patterns/patterns_statute.py
corpus_patterns/patterns_unit.py
corpus_patterns/tokens.py
corpus_patterns/tokens_infix.py
corpus_patterns/tokens_sfxpfx.py
corpus_patterns/tokens_single.py
corpus_patterns/utils.py
corpus_patterns-0.1.2.dist-info/METADATA
corpus_patterns-0.1.2.dist-info/WHEEL
corpus_patterns-0.1.2.dist-info/RECORD
