Metadata-Version: 2.1
Name: corpus-patterns
Version: 0.1.2
Summary: Building blocks for spacy Matcher patterns
Home-page: https://mv3.dev
Author: Marcelino G. Veloso III
Author-email: contact@mv3.dev
Requires-Python: >=3.11,<4.0
Classifier: Programming Language :: Python :: 3
Classifier: Programming Language :: Python :: 3.11
Classifier: Programming Language :: Python :: 3.12
Requires-Dist: environs (>=9.5.0,<10.0.0)
Requires-Dist: inflect (>=7.0,<8.0)
Requires-Dist: rich (>=13.7.0,<14.0.0)
Requires-Dist: roman (>=4.1,<5.0)
Requires-Dist: spacy[apple] (>=3.7.2,<4.0.0)
Requires-Dist: sqlite-utils (>=3.36,<4.0)
Project-URL: Documentation, https://justmars.github.io/corpus-patterns
Project-URL: Repository, https://github.com/justmars/corpus-patterns
